pmon/__init__.py
pmon/cli.py
pmon/utils.py
pmon-0.2.1.dist-info/entry_points.txt
pmon-0.2.1.dist-info/WHEEL
pmon-0.2.1.dist-info/METADATA
pmon-0.2.1.dist-info/RECORD
